README.md
setup.cfg
setup.py
strongdm/__init__.py
strongdm/account_attachments_pb2.py
strongdm/account_attachments_pb2_grpc.py
strongdm/account_grants_pb2.py
strongdm/account_grants_pb2_grpc.py
strongdm/accounts_pb2.py
strongdm/accounts_pb2_grpc.py
strongdm/client.py
strongdm/drivers_pb2.py
strongdm/drivers_pb2_grpc.py
strongdm/errors.py
strongdm/models.py
strongdm/nodes_pb2.py
strongdm/nodes_pb2_grpc.py
strongdm/options_pb2.py
strongdm/options_pb2_grpc.py
strongdm/plumbing.py
strongdm/resources_pb2.py
strongdm/resources_pb2_grpc.py
strongdm/role_attachments_pb2.py
strongdm/role_attachments_pb2_grpc.py
strongdm/role_grants_pb2.py
strongdm/role_grants_pb2_grpc.py
strongdm/roles_pb2.py
strongdm/roles_pb2_grpc.py
strongdm/spec_pb2.py
strongdm/spec_pb2_grpc.py
strongdm/svc.py
strongdm/tags_pb2.py
strongdm/tags_pb2_grpc.py
strongdm.egg-info/PKG-INFO
strongdm.egg-info/SOURCES.txt
strongdm.egg-info/dependency_links.txt
strongdm.egg-info/requires.txt
strongdm.egg-info/top_level.txt