Metadata-Version: 2.1
Name: strongdm
Version: 1.0.13
Summary: strongDM SDK for the Python programming language.
Home-page: https://github.com/strongdm/strongdm-sdk-python
Author: strongDM Team
Author-email: sdk-feedback@strongdm.com
License: apache-2.0
Download-URL: https://github.com/strongdm/strongdm-sdk-python/archive/v1.0.13.tar.gz
Keywords: strongDM,sdm,api,automation,security,audit,database,server,ssh,rdp
Platform: UNKNOWN
Classifier: Development Status :: 4 - Beta
Classifier: Intended Audience :: Developers
Classifier: Topic :: Security
Classifier: License :: OSI Approved :: Apache Software License
Classifier: Programming Language :: Python :: 3
